py_generator_build_backend/__init__.py
py_generator_build_backend/util.py
py_generator_build_backend-1.1.0.dist-info/METADATA
py_generator_build_backend-1.1.0.dist-info/WHEEL
py_generator_build_backend-1.1.0.dist-info/RECORD
