Metadata-Version: 2.4
Name: py-generator-build-backend
Version: 1.1.0
Summary: A Python build backend designed to wrap Python package generators into a PEP 517 compatible source tree
Author-email: Jeremy Fleischman <jeremyfleischman@gmail.com>
Requires-Python: >=3.9
Requires-Dist: expandvars
Requires-Dist: packaging
Requires-Dist: platformdirs
Requires-Dist: pyproject-hooks
